qazaq_transliterator/__init__.py
qazaq_transliterator/qazaq_transliterator.py
qazaq_transliterator-2.0.dist-info/LICENSE
qazaq_transliterator-2.0.dist-info/METADATA
qazaq_transliterator-2.0.dist-info/WHEEL
qazaq_transliterator-2.0.dist-info/top_level.txt
qazaq_transliterator-2.0.dist-info/RECORD
