Metadata-Version: 2.1
Name: qazaq-transliterator
Version: 2.0
Summary: Transliteration of the old Kazakh alphabet into a new one
Home-page: https://github.com/altynbek07/python-qazaq-transliterator
Author: Altynbek
Author-email: altynbek.kazezov.97@gmail.com
License: UNKNOWN
Keywords: translit,transliteration,transliterator,qazaq,kazakh,python,latin
Platform: UNKNOWN
Classifier: Programming Language :: Python
Classifier: Programming Language :: Python :: 2.7
Classifier: Programming Language :: Python :: 3
Classifier: Programming Language :: Python :: 3.4
Classifier: Programming Language :: Python :: 3.5
Classifier: Programming Language :: Python :: 3.6
Classifier: Programming Language :: Python :: Implementation :: PyPy
Classifier: Intended Audience :: Developers
Classifier: Operating System :: OS Independent
Requires-Dist: transliterate (>=1.10.2)
